pmpt/DB.py
pmpt/__init__.py
pmpt/__main__.py
pmpt/environment.py
pmpt/install.py
pmpt/search.py
pmpt/source.py
pmpt/update.py
pmpt/util.py
pmpt/web.py
pmpt/data/__init__.py
pmpt/data/index.html
pmpt/data/statics/css/bootstrap-icons.min.css
pmpt/data/statics/css/bootstrap.min.css
pmpt/data/statics/fonts/bootstrap-icons.woff2
pmpt/data/statics/img/loading.svg
pmpt/data/statics/js/bootstrap.bundle.min.js
pmpt/data/statics/js/jquery-3.7.1.min.js
pmpt-1.0.5.24.dist-info/METADATA
pmpt-1.0.5.24.dist-info/WHEEL
pmpt-1.0.5.24.dist-info/entry_points.txt
pmpt-1.0.5.24.dist-info/top_level.txt
pmpt-1.0.5.24.dist-info/RECORD
