Metadata-Version: 2.1
Name: pmpt
Version: 1.0.5.24
Summary: A Python Package Advanced Manager
Home-page: UNKNOWN
Author: MoYan
Author-email: moyan@moyanjdc.top
License: UNKNOWN
Platform: UNKNOWN
Classifier: Development Status :: 3 - Alpha
Classifier: Intended Audience :: Developers
Classifier: License :: OSI Approved :: MIT License
Classifier: Programming Language :: Python :: 3
Classifier: Programming Language :: Python :: 3.7
Classifier: Programming Language :: Python :: 3.8
Classifier: Programming Language :: Python :: 3.9
Requires-Dist: click (==8.1.7)
Requires-Dist: dill (==0.3.8)
Requires-Dist: loguru (==0.7.2)
Requires-Dist: moyanlib (>=1.5.1712028240)
Requires-Dist: platformdirs (==4.2.0)
Requires-Dist: psutil (==5.9.8)
Requires-Dist: requests (>=2.31.0)
Requires-Dist: rich (==13.7.1)
Requires-Dist: tinydb (==4.8.0)
Requires-Dist: tqdm (==4.66.2)
Requires-Dist: zstandard (==0.22.0)
Provides-Extra: web
Requires-Dist: flask (>=3.0.2) ; extra == 'web'
Requires-Dist: flask-caching (==2.1.0) ; extra == 'web'
